harkness/__init__.py
harkness/create_ply.py
harkness-1.0.5.dist-info/LICENSE
harkness-1.0.5.dist-info/METADATA
harkness-1.0.5.dist-info/WHEEL
harkness-1.0.5.dist-info/top_level.txt
harkness-1.0.5.dist-info/RECORD
