Metadata-Version: 2.1
Name: harkness
Version: 1.0.5
Summary: A python library for generating VR-friendly visualization files from pandas dataframes.
Author-email: Kristina Collins <kvcollins@spacescience.org>
License: MIT License
Project-URL: Homepage, https://github.com/KCollins/harkness
Project-URL: Bug Tracker, https://github.com/KCollins/harkness/issues
Project-URL: Changelog, https://github.com/KCollins/harkness/releases
Classifier: Programming Language :: Python :: 3
Classifier: License :: OSI Approved :: MIT License
Classifier: Intended Audience :: Developers
Requires-Python: >=3.6
License-File: LICENSE
Requires-Dist: matplotlib
Requires-Dist: pandas
